app/__init__.py
app/_version.py
app/config.py
app/resume_enhancer.py
app/scripts.py
app/utils.py
resume_enhancer-1.0.2.dist-info/METADATA
resume_enhancer-1.0.2.dist-info/WHEEL
resume_enhancer-1.0.2.dist-info/entry_points.txt
resume_enhancer-1.0.2.dist-info/licenses/LICENSE
resume_enhancer-1.0.2.dist-info/RECORD
