Metadata-Version: 2.3
Name: resume-enhancer
Version: 1.0.2
Summary: A CLI tool for optimizing and tailoring resumes based on job descriptions using AI.
Author-email: Harshil Patel <26harshilpatel11@gmail.com>
License: MIT
Requires-Python: >=3.11
Requires-Dist: annotated-types==0.7.0
Requires-Dist: anyio==4.5.0
Requires-Dist: certifi==2024.8.30
Requires-Dist: charset-normalizer==3.3.2
Requires-Dist: colorama==0.4.6
Requires-Dist: distro==1.9.0
Requires-Dist: groq==0.11.0
Requires-Dist: h11==0.14.0
Requires-Dist: halo==0.0.31
Requires-Dist: httpcore==1.0.5
Requires-Dist: httpx==0.27.2
Requires-Dist: idna==3.10
Requires-Dist: jiter==0.5.0
Requires-Dist: log-symbols==0.0.14
Requires-Dist: lxml==5.3.0
Requires-Dist: openai==1.46.0
Requires-Dist: pydantic-core==2.23.4
Requires-Dist: pydantic==2.9.2
Requires-Dist: pypdf
Requires-Dist: python-docx==1.1.2
Requires-Dist: requests==2.32.3
Requires-Dist: six==1.16.0
Requires-Dist: sniffio==1.3.1
Requires-Dist: spinners==0.0.24
Requires-Dist: termcolor==2.4.0
Requires-Dist: tomli==2.0.2
Requires-Dist: tqdm==4.66.5
Requires-Dist: typing-extensions==4.12.2
Requires-Dist: urllib3==2.2.3
Provides-Extra: dev
Requires-Dist: black==24.10.0; extra == 'dev'
Requires-Dist: flake8; extra == 'dev'
Requires-Dist: pre-commit==4.0.1; extra == 'dev'
Requires-Dist: pytest-xdist==3.6.1; extra == 'dev'
Requires-Dist: pytest==8.3.3; extra == 'dev'
